[{"time":74.572,"username":"ElenaV","userId":"ogUNp3LyAQ","contestId":"22bXwSwUdT"},{"time":74.361,"username":"tugrik","userId":"CSIg5d5Lin","contestId":"22bXwSwUdT"},{"time":68.262,"username":"Telecom","userId":"xa5SQIppDN","contestId":"22bXwSwUdT"},{"time":62.992,"username":"Eric","userId":"HUOFwtqM39","contestId":"22bXwSwUdT"},{"time":74.606,"username":"Kostik","userId":"q1Q38ckGiK","contestId":"22bXwSwUdT"},{"time":78.843,"username":"Davidoff","userId":"jrdEiHP4UU","contestId":"22bXwSwUdT"},{"time":71.837,"username":"truster","userId":"8bQr90wdup","contestId":"22bXwSwUdT"},{"time":80.028,"username":"lavr","userId":"2yCcruNhxh","contestId":"22bXwSwUdT"},{"time":70.904,"username":"chaika","userId":"ci08ZGuWC2","contestId":"22bXwSwUdT"},{"time":76.143,"username":"hogan","userId":"xEG2QCQQJn","contestId":"22bXwSwUdT"},{"time":74.925,"username":"gazel","userId":"ZJGKTxLCSj","contestId":"22bXwSwUdT"},{"time":68.446,"username":"demon","userId":"HdXLaEvnq0","contestId":"22bXwSwUdT"},{"time":77.425,"username":"Kiselchik","userId":"zhhdSXxS0m","contestId":"22bXwSwUdT"},{"time":73.505,"username":"Gugenot","userId":"n9AWl0ODIC","contestId":"22bXwSwUdT"},{"time":63.991,"username":"Teufel","userId":"2d8J4OGIuM","contestId":"22bXwSwUdT"},{"time":66.383,"username":"Korobochka","userId":"tEjWG0LH5b","contestId":"22bXwSwUdT"},{"time":71.066,"username":"Wrecker","userId":"wgU9D2McZ9","contestId":"22bXwSwUdT"},{"time":64.614,"username":"KocTuk","userId":"V2j16BXsUa","contestId":"22bXwSwUdT"},{"time":70.779,"username":"Cherepov","userId":"oq0k6irY13","contestId":"22bXwSwUdT"},{"time":69.838,"username":"Crazy","userId":"n1EF9yNxZ4","contestId":"22bXwSwUdT"},{"time":70.528,"username":"radminka","userId":"59h5HsqilL","contestId":"22bXwSwUdT"},{"time":64.061,"username":"realtor","userId":"xughIg536p","contestId":"22bXwSwUdT"},{"time":69.575,"username":"twist","userId":"AcLDEezjQ4","contestId":"22bXwSwUdT"},{"time":73.215,"username":"AZis","userId":"r4kvdWPlLA","contestId":"22bXwSwUdT"},{"time":73.658,"username":"MozG","userId":"vH02p2jKq2","contestId":"22bXwSwUdT"},{"time":64.401,"username":"kosmarium","userId":"t3uLSkjM2J","contestId":"22bXwSwUdT"},{"time":65.802,"username":"Bravenheart","userId":"gQN94BczW1","contestId":"22bXwSwUdT"},{"time":70.645,"username":"satair","userId":"glMXrooxoW","contestId":"22bXwSwUdT"},{"time":73.896,"username":"Moster","userId":"M8PQoBaihj","contestId":"22bXwSwUdT"},{"time":69.068,"username":"German","userId":"lT33kiOL4T","contestId":"22bXwSwUdT"},{"time":69.828,"username":"Kumarin","userId":"euQGYBgpDm","contestId":"22bXwSwUdT"},{"time":70.548,"username":"Energizer","userId":"r6y3GpAYZd","contestId":"22bXwSwUdT"},{"time":78.819,"username":"Spark","userId":"m6551zkLFi","contestId":"22bXwSwUdT"},{"time":66.095,"username":"sunset","userId":"PKmLfKc1JZ","contestId":"22bXwSwUdT"},{"time":75.237,"username":"Koenigsberg","userId":"O8X8cUgw5R","contestId":"22bXwSwUdT"},{"time":67.672,"username":"Pablo","userId":"gU4Lhx7vHN","contestId":"22bXwSwUdT"},{"time":77.104,"username":"Fess","userId":"vuTXE5XseP","contestId":"22bXwSwUdT"}]