[{"time":160.637,"username":"timmy","userId":"MOb2RIO7G0","contestId":"4QvbYCNiwy"},{"time":147.305,"username":"German","userId":"lT33kiOL4T","contestId":"4QvbYCNiwy"},{"time":164.739,"username":"Gaser","userId":"G19ElWRnTA","contestId":"4QvbYCNiwy"},{"time":153.915,"username":"Remex","userId":"3jB2rfyCSd","contestId":"4QvbYCNiwy"},{"time":161.504,"username":"gatekeeper","userId":"ZXox7p5iRL","contestId":"4QvbYCNiwy"},{"time":150.934,"username":"mighty","userId":"oWyRvFZyFM","contestId":"4QvbYCNiwy"}]