[{"time":81.246,"username":"realtor","userId":"xughIg536p","contestId":"6BRsR3gLNQ"},{"time":82.94,"username":"dimkapimka","userId":"OscxOTzfLA","contestId":"6BRsR3gLNQ"},{"time":82.801,"username":"alarm","userId":"4RL8g6NmQG","contestId":"6BRsR3gLNQ"},{"time":85.881,"username":"Taiga","userId":"brl9S9awe8","contestId":"6BRsR3gLNQ"},{"time":78.599,"username":"bodiroga","userId":"TFcY4B2JsF","contestId":"6BRsR3gLNQ"},{"time":86.636,"username":"German","userId":"lT33kiOL4T","contestId":"6BRsR3gLNQ"},{"time":82.04,"username":"eZZg","userId":"yVcb29myV9","contestId":"6BRsR3gLNQ"},{"time":78.608,"username":"Spark","userId":"m6551zkLFi","contestId":"6BRsR3gLNQ"},{"time":85.022,"username":"radminka","userId":"59h5HsqilL","contestId":"6BRsR3gLNQ"},{"time":82.528,"username":"headvision","userId":"Ghwug6N5M4","contestId":"6BRsR3gLNQ"},{"time":85.677,"username":"Dilly","userId":"DPiau3cnQ3","contestId":"6BRsR3gLNQ"},{"time":81.349,"username":"Moster","userId":"M8PQoBaihj","contestId":"6BRsR3gLNQ"},{"time":84.585,"username":"Margo","userId":"2ClZvL60Ff","contestId":"6BRsR3gLNQ"},{"time":79.951,"username":"alchemist","userId":"pNih4vtYln","contestId":"6BRsR3gLNQ"},{"time":83.341,"username":"mixailo","userId":"uTNim4dSZq","contestId":"6BRsR3gLNQ"},{"time":79.079,"username":"Oxbla","userId":"XlYsTfOQ7t","contestId":"6BRsR3gLNQ"},{"time":83.745,"username":"Bravenheart","userId":"gQN94BczW1","contestId":"6BRsR3gLNQ"},{"time":83.68,"username":"Gavryusha","userId":"IzfIutYfOb","contestId":"6BRsR3gLNQ"},{"time":85.608,"username":"Artemchik","userId":"ElLFHDPZOE","contestId":"6BRsR3gLNQ"},{"time":86.175,"username":"Zebra","userId":"zxy05JyuCp","contestId":"6BRsR3gLNQ"},{"time":78.152,"username":"Amlet","userId":"DwgJmD2ENg","contestId":"6BRsR3gLNQ"},{"time":95.764,"username":"DimSpeed","userId":"ibqVXeSsB8","contestId":"6BRsR3gLNQ"},{"time":96.357,"username":"Antoha","userId":"UmLPoZ7s9A","contestId":"6BRsR3gLNQ"},{"time":89.168,"username":"Energizer","userId":"r6y3GpAYZd","contestId":"6BRsR3gLNQ"},{"time":93.081,"username":"marta","userId":"tO7i9RNCCw","contestId":"6BRsR3gLNQ"},{"time":92.984,"username":"otrada","userId":"IUXKulNiDe","contestId":"6BRsR3gLNQ"},{"time":86.257,"username":"Antares","userId":"T3l6HJKOMm","contestId":"6BRsR3gLNQ"},{"time":85.234,"username":"lavr","userId":"2yCcruNhxh","contestId":"6BRsR3gLNQ"},{"time":95.461,"username":"zxspectrum","userId":"oVXbesireW","contestId":"6BRsR3gLNQ"},{"time":97.391,"username":"Hoster","userId":"UlcHqQNx9Z","contestId":"6BRsR3gLNQ"},{"time":97.309,"username":"Artem","userId":"EWRf6hAaNP","contestId":"6BRsR3gLNQ"},{"time":86.736,"username":"Люба777","userId":"b9g4KMa7xu","contestId":"6BRsR3gLNQ"},{"time":79.518,"username":"mihan","userId":"oGkbP0bXcy","contestId":"6BRsR3gLNQ"},{"time":89.68,"username":"demon","userId":"HdXLaEvnq0","contestId":"6BRsR3gLNQ"},{"time":96.585,"username":"Eric","userId":"HUOFwtqM39","contestId":"6BRsR3gLNQ"},{"time":79.471,"username":"lecter","userId":"CUGqZbAdDN","contestId":"6BRsR3gLNQ"},{"time":97.942,"username":"junky","userId":"EULIDuUMff","contestId":"6BRsR3gLNQ"},{"time":51.619,"username":"formin","userId":"R3aZtfr1s3","contestId":"6BRsR3gLNQ"},{"time":84.303,"username":"s4n9","userId":"ai5Juu7L58","contestId":"6BRsR3gLNQ"}]