[{"time":347.2,"username":"mighty","userId":"oWyRvFZyFM","contestId":"70vv4Gv8ga"},{"time":368.363,"username":"headvision","userId":"Ghwug6N5M4","contestId":"70vv4Gv8ga"},{"time":371.113,"username":"sharaban","userId":"tlaCbnhUPW","contestId":"70vv4Gv8ga"},{"time":349.575,"username":"Irin","userId":"4GwJgd9sjA","contestId":"70vv4Gv8ga"},{"time":358.284,"username":"Noir","userId":"48MwdVABxn","contestId":"70vv4Gv8ga"},{"time":373.771,"username":"NoSound","userId":"OMF2I2bZbm","contestId":"70vv4Gv8ga"},{"time":381.12399999999997,"username":"Hutch","userId":"UTxdBytT5r","contestId":"70vv4Gv8ga"},{"time":344.4,"username":"pimvic","userId":"KupWJ3dPn9","contestId":"70vv4Gv8ga"},{"time":378.369,"username":"emerald","userId":"oKlDxpGCHc","contestId":"70vv4Gv8ga"},{"time":342.54299999999995,"username":"strelka","userId":"tQfcC7XCdn","contestId":"70vv4Gv8ga"},{"time":382.53300000000007,"username":"hogan","userId":"xEG2QCQQJn","contestId":"70vv4Gv8ga"},{"time":380.823,"username":"Alexander","userId":"FtPNo0wmUz","contestId":"70vv4Gv8ga"},{"time":393.571,"username":"hoffman","userId":"f0hLuzIBxh","contestId":"70vv4Gv8ga"},{"time":371.965,"username":"zFruit","userId":"msPbxEOCNW","contestId":"70vv4Gv8ga"},{"time":343.00600000000003,"username":"BugFix","userId":"4IXrS4LiB3","contestId":"70vv4Gv8ga"},{"time":382.14300000000003,"username":"diezel","userId":"Qu9nKCtD1O","contestId":"70vv4Gv8ga"},{"time":378.68399999999997,"username":"turonix","userId":"x9vZrPl0e6","contestId":"70vv4Gv8ga"},{"time":357.27,"username":"marta","userId":"tO7i9RNCCw","contestId":"70vv4Gv8ga"},{"time":367.139,"username":"twist","userId":"AcLDEezjQ4","contestId":"70vv4Gv8ga"},{"time":381.77700000000004,"username":"northstar","userId":"KI3daYrAfT","contestId":"70vv4Gv8ga"},{"time":358.27000000000004,"username":"Denych","userId":"4oAHFyVqLT","contestId":"70vv4Gv8ga"},{"time":360.202,"username":"wizzle","userId":"HvY0aJUU6H","contestId":"70vv4Gv8ga"},{"time":362.70200000000006,"username":"hamed","userId":"oxjmHRUZ4Z","contestId":"70vv4Gv8ga"},{"time":390.437,"username":"fanny","userId":"wYL1O4sPF0","contestId":"70vv4Gv8ga"}]