[{"time":40.184,"username":"fatok","userId":"wPJg0ahCMz","contestId":"9tGylpEWy7"},{"time":38.473,"username":"Aless","userId":"wSbrq0e4NY","contestId":"9tGylpEWy7"},{"time":39.557,"username":"arverson","userId":"w0JFdFKANi","contestId":"9tGylpEWy7"},{"time":37.973,"username":"defender","userId":"fafCy9FcG5","contestId":"9tGylpEWy7"},{"time":37.653,"username":"timanu","userId":"KjF1tu3U9E","contestId":"9tGylpEWy7"},{"time":40.635,"username":"Fiolent","userId":"Hv2K0RxqA1","contestId":"9tGylpEWy7"},{"time":39.624,"username":"Listik","userId":"U4Rf5EFH0n","contestId":"9tGylpEWy7"},{"time":39.034,"username":"Xlat","userId":"WtV2U0BpZZ","contestId":"9tGylpEWy7"}]