[{"time":127.836,"username":"Taiga","userId":"brl9S9awe8","contestId":"9UWyTQ4WJa"},{"time":138.615,"username":"Gilfor","userId":"OIkFqWF7g3","contestId":"9UWyTQ4WJa"},{"time":148.246,"username":"Rainbow","userId":"YIEQL1qcRS","contestId":"9UWyTQ4WJa"},{"time":126.577,"username":"junky","userId":"EULIDuUMff","contestId":"9UWyTQ4WJa"},{"time":122.249,"username":"Sensi","userId":"jRy3fU7oKL","contestId":"9UWyTQ4WJa"},{"time":136.179,"username":"dimkapimka","userId":"OscxOTzfLA","contestId":"9UWyTQ4WJa"},{"time":140.247,"username":"Moster","userId":"M8PQoBaihj","contestId":"9UWyTQ4WJa"},{"time":121.113,"username":"Jobru","userId":"QyLF17xoue","contestId":"9UWyTQ4WJa"},{"time":131.682,"username":"Crazy","userId":"n1EF9yNxZ4","contestId":"9UWyTQ4WJa"},{"time":135.405,"username":"Magnum","userId":"RN1adrQOpv","contestId":"9UWyTQ4WJa"},{"time":145.068,"username":"gazel","userId":"ZJGKTxLCSj","contestId":"9UWyTQ4WJa"},{"time":147.929,"username":"pimvic","userId":"KupWJ3dPn9","contestId":"9UWyTQ4WJa"},{"time":131.279,"username":"NoSound","userId":"OMF2I2bZbm","contestId":"9UWyTQ4WJa"},{"time":141.446,"username":"thunderstorm","userId":"ss2WVEVHi3","contestId":"9UWyTQ4WJa"},{"time":134.048,"username":"Spark","userId":"m6551zkLFi","contestId":"9UWyTQ4WJa"},{"time":129.846,"username":"MozG","userId":"vH02p2jKq2","contestId":"9UWyTQ4WJa"},{"time":130.11,"username":"zFruit","userId":"msPbxEOCNW","contestId":"9UWyTQ4WJa"},{"time":145.822,"username":"Pashke","userId":"d1Ulto5BrA","contestId":"9UWyTQ4WJa"},{"time":127.018,"username":"sharaban","userId":"tlaCbnhUPW","contestId":"9UWyTQ4WJa"},{"time":143.485,"username":"turonix","userId":"x9vZrPl0e6","contestId":"9UWyTQ4WJa"},{"time":125.98,"username":"Irin","userId":"4GwJgd9sjA","contestId":"9UWyTQ4WJa"},{"time":138.674,"username":"diezel","userId":"Qu9nKCtD1O","contestId":"9UWyTQ4WJa"},{"time":139.664,"username":"volchanna","userId":"OAfBcFGlob","contestId":"9UWyTQ4WJa"},{"time":139.01,"username":"Sterl","userId":"3lh4AIdJCB","contestId":"9UWyTQ4WJa"},{"time":124.75,"username":"Pablo","userId":"gU4Lhx7vHN","contestId":"9UWyTQ4WJa"},{"time":137.993,"username":"Roman","userId":"IQnLwda1cb","contestId":"9UWyTQ4WJa"},{"time":140.619,"username":"radminka","userId":"59h5HsqilL","contestId":"9UWyTQ4WJa"}]