[{"time":40.394,"username":"lavr","userId":"2yCcruNhxh","contestId":"aLHvNsH79g"},{"time":42.111,"username":"German","userId":"lT33kiOL4T","contestId":"aLHvNsH79g"},{"time":42.208,"username":"Hippy","userId":"dmZZIpQxXh","contestId":"aLHvNsH79g"},{"time":41.915,"username":"yura","userId":"VTLCmSYaID","contestId":"aLHvNsH79g"},{"time":42.097,"username":"fanny","userId":"wYL1O4sPF0","contestId":"aLHvNsH79g"},{"time":40.647,"username":"Yaroslav","userId":"pKKThXr0og","contestId":"aLHvNsH79g"},{"time":46.033,"username":"gazel","userId":"ZJGKTxLCSj","contestId":"aLHvNsH79g"},{"time":43.69,"username":"gatekeeper","userId":"ZXox7p5iRL","contestId":"aLHvNsH79g"},{"time":45.618,"username":"Zvezdochka","userId":"JaDHISTlvW","contestId":"aLHvNsH79g"},{"time":41.486,"username":"lecter","userId":"CUGqZbAdDN","contestId":"aLHvNsH79g"},{"time":39.762,"username":"Taiga","userId":"brl9S9awe8","contestId":"aLHvNsH79g"},{"time":44.279,"username":"aqualang","userId":"V8EQFilixt","contestId":"aLHvNsH79g"},{"time":43.379,"username":"Nikolay","userId":"XUCMOQqV2Q","contestId":"aLHvNsH79g"}]