[{"time":47.834,"username":"eZZg","userId":"yVcb29myV9","contestId":"ble3AoaZKs"},{"time":48.325,"username":"shurisk","userId":"1V6lDDKVey","contestId":"ble3AoaZKs"},{"time":46.602,"username":"noBody","userId":"xWZwOiUgsG","contestId":"ble3AoaZKs"},{"time":45.734,"username":"Remex","userId":"3jB2rfyCSd","contestId":"ble3AoaZKs"},{"time":45.451,"username":"Scorpion","userId":"Fv5hg1ehgW","contestId":"ble3AoaZKs"},{"time":46.144,"username":"lavr","userId":"2yCcruNhxh","contestId":"ble3AoaZKs"},{"time":46.549,"username":"Reformer","userId":"EA2XBxV7nH","contestId":"ble3AoaZKs"},{"time":46.805,"username":"CatDog","userId":"E4OLXNju1f","contestId":"ble3AoaZKs"},{"time":45.054,"username":"MozG","userId":"vH02p2jKq2","contestId":"ble3AoaZKs"},{"time":47.405,"username":"Zorik","userId":"h6wgkiBBQB","contestId":"ble3AoaZKs"},{"time":47.902,"username":"Oriyonfarr","userId":"Y9YfOkWiFA","contestId":"ble3AoaZKs"},{"time":45.662,"username":"Telecom","userId":"xa5SQIppDN","contestId":"ble3AoaZKs"},{"time":46.214,"username":"Sergei","userId":"rKTk6Elzkz","contestId":"ble3AoaZKs"},{"time":45.361,"username":"Bravenheart","userId":"gQN94BczW1","contestId":"ble3AoaZKs"},{"time":48.112,"username":"Idall","userId":"Min24Im8Gc","contestId":"ble3AoaZKs"}]