[{"time":62.969,"username":"Werter","userId":"bqjh0x9Lwr","contestId":"D2El9vobvX"},{"time":70.87700000000001,"username":"northstar","userId":"KI3daYrAfT","contestId":"D2El9vobvX"},{"time":64.689,"username":"Managerino","userId":"qTldU0ILjC","contestId":"D2El9vobvX"},{"time":65.969000000000008,"username":"Dilly","userId":"DPiau3cnQ3","contestId":"D2El9vobvX"},{"time":62.183,"username":"Idall","userId":"Min24Im8Gc","contestId":"D2El9vobvX"},{"time":62.601,"username":"kamay","userId":"xTkMRPArvV","contestId":"D2El9vobvX"},{"time":68.047000000000011,"username":"deel","userId":"rA15z6kfCy","contestId":"D2El9vobvX"},{"time":63.147,"username":"Moster","userId":"M8PQoBaihj","contestId":"D2El9vobvX"},{"time":63.815999999999995,"username":"Riba","userId":"KE3b7mCwto","contestId":"D2El9vobvX"},{"time":60.233,"username":"Gugenot","userId":"n9AWl0ODIC","contestId":"D2El9vobvX"},{"time":66.202,"username":"Sonya","userId":"E0MkSLsSdU","contestId":"D2El9vobvX"},{"time":70.509,"username":"Might","userId":"pTvODzcpbt","contestId":"D2El9vobvX"},{"time":63.006,"username":"Sergei","userId":"rKTk6Elzkz","contestId":"D2El9vobvX"},{"time":69.234,"username":"Scorpion","userId":"Fv5hg1ehgW","contestId":"D2El9vobvX"},{"time":62.439,"username":"Kiselchik","userId":"zhhdSXxS0m","contestId":"D2El9vobvX"},{"time":60.54,"username":"svp","userId":"HHhd1jVNBP","contestId":"D2El9vobvX"},{"time":65.964,"username":"petkap","userId":"SClN7JFxqZ","contestId":"D2El9vobvX"},{"time":61.836,"username":"Solowind","userId":"Ltp2XuJpFp","contestId":"D2El9vobvX"}]