[{"time":135.837,"username":"chaika","userId":"ci08ZGuWC2","contestId":"EOZAoiqyjP"},{"time":140.698,"username":"hoffman","userId":"f0hLuzIBxh","contestId":"EOZAoiqyjP"},{"time":126.924,"username":"petkap","userId":"SClN7JFxqZ","contestId":"EOZAoiqyjP"},{"time":127.13,"username":"chuk","userId":"KXNpCHDPFG","contestId":"EOZAoiqyjP"},{"time":138.071,"username":"sharaban","userId":"tlaCbnhUPW","contestId":"EOZAoiqyjP"},{"time":130.519,"username":"lecter","userId":"CUGqZbAdDN","contestId":"EOZAoiqyjP"},{"time":145.434,"username":"Sterl","userId":"3lh4AIdJCB","contestId":"EOZAoiqyjP"},{"time":137.306,"username":"Vladislav","userId":"B5tqWjWnFA","contestId":"EOZAoiqyjP"},{"time":147.262,"username":"nurlan","userId":"pAYQxoj0Ev","contestId":"EOZAoiqyjP"},{"time":129.129,"username":"Trident","userId":"36PDZE4lc7","contestId":"EOZAoiqyjP"},{"time":137.813,"username":"timmy","userId":"MOb2RIO7G0","contestId":"EOZAoiqyjP"},{"time":138.943,"username":"Jalex","userId":"WJJ1Sjhxre","contestId":"EOZAoiqyjP"},{"time":125.571,"username":"Zvezdochka","userId":"JaDHISTlvW","contestId":"EOZAoiqyjP"},{"time":126.221,"username":"satair","userId":"glMXrooxoW","contestId":"EOZAoiqyjP"},{"time":129.505,"username":"ангелина","userId":"GBLMYbMyoZ","contestId":"EOZAoiqyjP"}]