[{"time":81.782,"username":"Nataliana","userId":"5kRb69BwR3","contestId":"F9EaGID8Ob"},{"time":86.835,"username":"kryab","userId":"MxZLOYn3Xe","contestId":"F9EaGID8Ob"},{"time":79.422,"username":"Koder","userId":"AvaimcaYPE","contestId":"F9EaGID8Ob"},{"time":87.242,"username":"Stefanie","userId":"cfw9xXcIyi","contestId":"F9EaGID8Ob"},{"time":84.124,"username":"Zebra","userId":"zxy05JyuCp","contestId":"F9EaGID8Ob"},{"time":82.496,"username":"defender","userId":"fafCy9FcG5","contestId":"F9EaGID8Ob"},{"time":79.021,"username":"Hippy","userId":"dmZZIpQxXh","contestId":"F9EaGID8Ob"},{"time":76.753,"username":"Tolik","userId":"xnk2S1z6Wn","contestId":"F9EaGID8Ob"},{"time":83.433,"username":"German","userId":"lT33kiOL4T","contestId":"F9EaGID8Ob"},{"time":88.283,"username":"JuliaStar","userId":"fFTXkbsswP","contestId":"F9EaGID8Ob"},{"time":78.777,"username":"Aless","userId":"wSbrq0e4NY","contestId":"F9EaGID8Ob"},{"time":77.387,"username":"emerald","userId":"oKlDxpGCHc","contestId":"F9EaGID8Ob"},{"time":80.633,"username":"eZZg","userId":"yVcb29myV9","contestId":"F9EaGID8Ob"},{"time":78.684,"username":"mihan","userId":"oGkbP0bXcy","contestId":"F9EaGID8Ob"},{"time":77.701,"username":"Nata1987","userId":"e64K7EOPLP","contestId":"F9EaGID8Ob"},{"time":79.609,"username":"Hutch","userId":"UTxdBytT5r","contestId":"F9EaGID8Ob"}]