[{"time":97.873,"username":"_Andrey_","userId":"VNVJV4ejjY","contestId":"g6AubL6xQZ"},{"time":85.624,"username":"Sergei","userId":"rKTk6Elzkz","contestId":"g6AubL6xQZ"},{"time":87.997,"username":"fatok","userId":"wPJg0ahCMz","contestId":"g6AubL6xQZ"},{"time":100.992,"username":"Ingvar","userId":"ZIAgw5cEJe","contestId":"g6AubL6xQZ"},{"time":78.075,"username":"Garry","userId":"3rXJL0dacs","contestId":"g6AubL6xQZ"},{"time":92.934,"username":"otrada","userId":"IUXKulNiDe","contestId":"g6AubL6xQZ"},{"time":80.619,"username":"Energizer","userId":"r6y3GpAYZd","contestId":"g6AubL6xQZ"},{"time":81.211,"username":"Bokser","userId":"iFbRybereK","contestId":"g6AubL6xQZ"},{"time":99.309,"username":"tiger","userId":"E13LiAUW4M","contestId":"g6AubL6xQZ"},{"time":88.496,"username":"lipton","userId":"Jba8slrEfV","contestId":"g6AubL6xQZ"},{"time":100.244,"username":"Thunderbird","userId":"l2AZobIsml","contestId":"g6AubL6xQZ"},{"time":89.136,"username":"Wrecker","userId":"wgU9D2McZ9","contestId":"g6AubL6xQZ"},{"time":83.064,"username":"mighty","userId":"oWyRvFZyFM","contestId":"g6AubL6xQZ"},{"time":86.234,"username":"Mika","userId":"8X1SzBg0JH","contestId":"g6AubL6xQZ"},{"time":80.741,"username":"nagel","userId":"dVkcFX0cE1","contestId":"g6AubL6xQZ"},{"time":97.475,"username":"Artyom","userId":"ta0gMDm931","contestId":"g6AubL6xQZ"},{"time":95.789,"username":"Managerino","userId":"qTldU0ILjC","contestId":"g6AubL6xQZ"},{"time":82.698,"username":"wizzle","userId":"HvY0aJUU6H","contestId":"g6AubL6xQZ"},{"time":95.873,"username":"CatDog","userId":"E4OLXNju1f","contestId":"g6AubL6xQZ"},{"time":83.629,"username":"alchemist","userId":"pNih4vtYln","contestId":"g6AubL6xQZ"},{"time":92.247,"username":"Bravenheart","userId":"gQN94BczW1","contestId":"g6AubL6xQZ"},{"time":99.763,"username":"Alexander","userId":"FtPNo0wmUz","contestId":"g6AubL6xQZ"},{"time":105.76,"username":"Zebra","userId":"zxy05JyuCp","contestId":"g6AubL6xQZ"},{"time":97.176,"username":"noBody","userId":"xWZwOiUgsG","contestId":"g6AubL6xQZ"},{"time":96.318,"username":"Antoha","userId":"UmLPoZ7s9A","contestId":"g6AubL6xQZ"},{"time":92.671,"username":"Filipok","userId":"5tiXLJhl0V","contestId":"g6AubL6xQZ"},{"time":93.618,"username":"Trident","userId":"36PDZE4lc7","contestId":"g6AubL6xQZ"},{"time":91.725,"username":"Tully","userId":"U18J2QmFf4","contestId":"g6AubL6xQZ"},{"time":87.753,"username":"terminator","userId":"mvZuv4N7TI","contestId":"g6AubL6xQZ"},{"time":93.504,"username":"marta","userId":"tO7i9RNCCw","contestId":"g6AubL6xQZ"},{"time":109.082,"username":"junky","userId":"EULIDuUMff","contestId":"g6AubL6xQZ"},{"time":78.607,"username":"twist","userId":"AcLDEezjQ4","contestId":"g6AubL6xQZ"},{"time":99.896,"username":"Dilly","userId":"DPiau3cnQ3","contestId":"g6AubL6xQZ"}]