[{"time":74.304,"username":"Frage","userId":"wt6YCq0Mqh","contestId":"gJftJrFT2D"},{"time":74.183,"username":"Margo","userId":"2ClZvL60Ff","contestId":"gJftJrFT2D"},{"time":76.371,"username":"Managerino","userId":"qTldU0ILjC","contestId":"gJftJrFT2D"},{"time":75.763,"username":"Koder","userId":"AvaimcaYPE","contestId":"gJftJrFT2D"},{"time":77.997,"username":"drews","userId":"BzwMxYYS3X","contestId":"gJftJrFT2D"},{"time":81.456,"username":"Xlat","userId":"WtV2U0BpZZ","contestId":"gJftJrFT2D"},{"time":77.819,"username":"JuliaStar","userId":"fFTXkbsswP","contestId":"gJftJrFT2D"},{"time":80.472,"username":"tosik","userId":"tGiOjoTX1H","contestId":"gJftJrFT2D"},{"time":71.994,"username":"uipx","userId":"vHmCHXcYsF","contestId":"gJftJrFT2D"},{"time":78.86,"username":"otrada","userId":"IUXKulNiDe","contestId":"gJftJrFT2D"},{"time":72.668,"username":"aqualang","userId":"V8EQFilixt","contestId":"gJftJrFT2D"},{"time":75.739,"username":"Taiga","userId":"brl9S9awe8","contestId":"gJftJrFT2D"},{"time":80.881,"username":"Stitch","userId":"Za1HN3dNKl","contestId":"gJftJrFT2D"},{"time":80.377,"username":"Sensi","userId":"jRy3fU7oKL","contestId":"gJftJrFT2D"},{"time":83.898,"username":"Infa","userId":"E6SXFmqkmd","contestId":"gJftJrFT2D"},{"time":84.547,"username":"kryab","userId":"MxZLOYn3Xe","contestId":"gJftJrFT2D"},{"time":83.688,"username":"radminka","userId":"59h5HsqilL","contestId":"gJftJrFT2D"},{"time":75.893,"username":"playa","userId":"6hceWKjc9h","contestId":"gJftJrFT2D"}]