[{"time":100.691,"username":"strelka","userId":"tQfcC7XCdn","contestId":"IeYvmXwk8J"},{"time":105.106,"username":"Crazy","userId":"n1EF9yNxZ4","contestId":"IeYvmXwk8J"},{"time":100.607,"username":"kosmarium","userId":"t3uLSkjM2J","contestId":"IeYvmXwk8J"},{"time":111.678,"username":"Jobru","userId":"QyLF17xoue","contestId":"IeYvmXwk8J"},{"time":106.791,"username":"danikus12","userId":"v3fMDT5xzl","contestId":"IeYvmXwk8J"},{"time":108.175,"username":"gatekeeper","userId":"ZXox7p5iRL","contestId":"IeYvmXwk8J"},{"time":103.327,"username":"Jalex","userId":"WJJ1Sjhxre","contestId":"IeYvmXwk8J"},{"time":105.402,"username":"tosik","userId":"tGiOjoTX1H","contestId":"IeYvmXwk8J"},{"time":105.499,"username":"Stenli","userId":"PPpEK97LbY","contestId":"IeYvmXwk8J"},{"time":103.286,"username":"playa","userId":"6hceWKjc9h","contestId":"IeYvmXwk8J"}]