[{"time":207.961,"username":"northstar","userId":"KI3daYrAfT","contestId":"iglUgyed28"},{"time":209.924,"username":"maxat","userId":"Xr41F2cAdl","contestId":"iglUgyed28"},{"time":224.178,"username":"Kumarin","userId":"euQGYBgpDm","contestId":"iglUgyed28"},{"time":207.975,"username":"Oriyonfarr","userId":"Y9YfOkWiFA","contestId":"iglUgyed28"},{"time":216.311,"username":"kamay","userId":"xTkMRPArvV","contestId":"iglUgyed28"},{"time":213.56,"username":"mixailo","userId":"uTNim4dSZq","contestId":"iglUgyed28"},{"time":205.275,"username":"Edifer","userId":"JgJNfzs48d","contestId":"iglUgyed28"},{"time":221.213,"username":"Artem","userId":"EWRf6hAaNP","contestId":"iglUgyed28"},{"time":211.463,"username":"Aless","userId":"wSbrq0e4NY","contestId":"iglUgyed28"},{"time":212.111,"username":"CatDog","userId":"E4OLXNju1f","contestId":"iglUgyed28"},{"time":212.069,"username":"MozG","userId":"vH02p2jKq2","contestId":"iglUgyed28"}]