[{"time":44.273,"username":"Solowind","userId":"Ltp2XuJpFp","contestId":"lNhMzJS2lO"},{"time":43.99,"username":"Tully","userId":"U18J2QmFf4","contestId":"lNhMzJS2lO"},{"time":45.895,"username":"Sonya","userId":"E0MkSLsSdU","contestId":"lNhMzJS2lO"},{"time":46.199,"username":"Troy","userId":"yZlVPqyl4J","contestId":"lNhMzJS2lO"},{"time":48.095,"username":"Kuso","userId":"scoca9Hxcv","contestId":"lNhMzJS2lO"},{"time":45.574,"username":"turonix","userId":"x9vZrPl0e6","contestId":"lNhMzJS2lO"},{"time":46.757,"username":"greenstar","userId":"2ETM6KN9sT","contestId":"lNhMzJS2lO"},{"time":45.524,"username":"lecter","userId":"CUGqZbAdDN","contestId":"lNhMzJS2lO"},{"time":44.183,"username":"Filipok","userId":"5tiXLJhl0V","contestId":"lNhMzJS2lO"},{"time":45.051,"username":"Noir","userId":"48MwdVABxn","contestId":"lNhMzJS2lO"},{"time":47.008,"username":"shurisk","userId":"1V6lDDKVey","contestId":"lNhMzJS2lO"},{"time":45.752,"username":"radminka","userId":"59h5HsqilL","contestId":"lNhMzJS2lO"},{"time":44.147,"username":"Stefanie","userId":"cfw9xXcIyi","contestId":"lNhMzJS2lO"},{"time":43.624,"username":"malex","userId":"sSrZuzz3hI","contestId":"lNhMzJS2lO"},{"time":48.339,"username":"Coral","userId":"eS04He69a0","contestId":"lNhMzJS2lO"},{"time":43.289,"username":"sharaban","userId":"tlaCbnhUPW","contestId":"lNhMzJS2lO"},{"time":44.619,"username":"Rhino","userId":"Ic0ZjHDwJy","contestId":"lNhMzJS2lO"},{"time":47.761,"username":"Efficient","userId":"HWAtybMQXa","contestId":"lNhMzJS2lO"},{"time":47.203,"username":"ruff","userId":"v5gqt9TN4u","contestId":"lNhMzJS2lO"}]