[{"time":76.342,"username":"Ofigist","userId":"Xc0W00RPcD","contestId":"mA6MK1edaD"},{"time":70.113,"username":"headvision","userId":"Ghwug6N5M4","contestId":"mA6MK1edaD"},{"time":68.06,"username":"Frage","userId":"wt6YCq0Mqh","contestId":"mA6MK1edaD"},{"time":66.926,"username":"Stitch","userId":"Za1HN3dNKl","contestId":"mA6MK1edaD"},{"time":68.347,"username":"Riba","userId":"KE3b7mCwto","contestId":"mA6MK1edaD"},{"time":72.731,"username":"arverson","userId":"w0JFdFKANi","contestId":"mA6MK1edaD"},{"time":77.468,"username":"Achilles","userId":"o0weiufq4s","contestId":"mA6MK1edaD"},{"time":71.771,"username":"eZZg","userId":"yVcb29myV9","contestId":"mA6MK1edaD"},{"time":66.782,"username":"Trident","userId":"36PDZE4lc7","contestId":"mA6MK1edaD"},{"time":72.135,"username":"Coral","userId":"eS04He69a0","contestId":"mA6MK1edaD"},{"time":70.306,"username":"diezel","userId":"Qu9nKCtD1O","contestId":"mA6MK1edaD"},{"time":71.227,"username":"kamay","userId":"xTkMRPArvV","contestId":"mA6MK1edaD"},{"time":72.441,"username":"dimazik","userId":"pnLz9Bm7ZO","contestId":"mA6MK1edaD"},{"time":71.02,"username":"mori","userId":"YSiAgFzgRt","contestId":"mA6MK1edaD"},{"time":70.583,"username":"Sonya","userId":"E0MkSLsSdU","contestId":"mA6MK1edaD"},{"time":66.636,"username":"tugrik","userId":"CSIg5d5Lin","contestId":"mA6MK1edaD"},{"time":73.996,"username":"dach","userId":"eCZxH8XM0e","contestId":"mA6MK1edaD"},{"time":66.971,"username":"Zvezdochka","userId":"JaDHISTlvW","contestId":"mA6MK1edaD"},{"time":69.53,"username":"Jobru","userId":"QyLF17xoue","contestId":"mA6MK1edaD"},{"time":68.193,"username":"Andrea","userId":"vwKVRoqmzX","contestId":"mA6MK1edaD"},{"time":71.842,"username":"turonix","userId":"x9vZrPl0e6","contestId":"mA6MK1edaD"},{"time":66.62,"username":"Kumarin","userId":"euQGYBgpDm","contestId":"mA6MK1edaD"},{"time":70.137,"username":"Crazy","userId":"n1EF9yNxZ4","contestId":"mA6MK1edaD"},{"time":69.781,"username":"JuliaStar","userId":"fFTXkbsswP","contestId":"mA6MK1edaD"},{"time":69.005,"username":"Jalex","userId":"WJJ1Sjhxre","contestId":"mA6MK1edaD"},{"time":67.157,"username":"Scorpion","userId":"Fv5hg1ehgW","contestId":"mA6MK1edaD"}]