[{"time":71.05,"username":"pimvic","userId":"KupWJ3dPn9","contestId":"NBrmAXycBH"},{"time":74.88,"username":"Droid","userId":"3vdLnr87eM","contestId":"NBrmAXycBH"},{"time":92.506,"username":"alarm","userId":"4RL8g6NmQG","contestId":"NBrmAXycBH"},{"time":86.734,"username":"Artemchik","userId":"ElLFHDPZOE","contestId":"NBrmAXycBH"},{"time":73.244,"username":"Energizer","userId":"r6y3GpAYZd","contestId":"NBrmAXycBH"},{"time":74.524,"username":"Kroman","userId":"uDip3s1t0Q","contestId":"NBrmAXycBH"},{"time":85.792,"username":"runanaru","userId":"wjYqejUa4n","contestId":"NBrmAXycBH"},{"time":86.065,"username":"AZis","userId":"r4kvdWPlLA","contestId":"NBrmAXycBH"},{"time":80.388,"username":"Ofigist","userId":"Xc0W00RPcD","contestId":"NBrmAXycBH"},{"time":79.885,"username":"emerald","userId":"oKlDxpGCHc","contestId":"NBrmAXycBH"},{"time":90.933,"username":"hamed","userId":"oxjmHRUZ4Z","contestId":"NBrmAXycBH"},{"time":74.43,"username":"Trident","userId":"36PDZE4lc7","contestId":"NBrmAXycBH"},{"time":86.485,"username":"Might","userId":"pTvODzcpbt","contestId":"NBrmAXycBH"},{"time":76.337,"username":"Solowind","userId":"Ltp2XuJpFp","contestId":"NBrmAXycBH"},{"time":87.963,"username":"Terra","userId":"pIy71rR1ZN","contestId":"NBrmAXycBH"},{"time":92.973,"username":"Xlat","userId":"WtV2U0BpZZ","contestId":"NBrmAXycBH"},{"time":86.767,"username":"realtor","userId":"xughIg536p","contestId":"NBrmAXycBH"},{"time":82.178,"username":"takumi","userId":"FYxjOFE7BV","contestId":"NBrmAXycBH"},{"time":78.407,"username":"Antares","userId":"T3l6HJKOMm","contestId":"NBrmAXycBH"},{"time":83.761,"username":"murr","userId":"wTrwQLDgos","contestId":"NBrmAXycBH"},{"time":78.976,"username":"dimas","userId":"N3KstJQA9W","contestId":"NBrmAXycBH"},{"time":80.485,"username":"PoisonGlen","userId":"C09urwrjlq","contestId":"NBrmAXycBH"},{"time":86.603,"username":"Wizard9","userId":"zBRIIvy64z","contestId":"NBrmAXycBH"},{"time":75.418,"username":"Fess","userId":"vuTXE5XseP","contestId":"NBrmAXycBH"},{"time":79.181,"username":"Tully","userId":"U18J2QmFf4","contestId":"NBrmAXycBH"},{"time":86.479,"username":"Dilly","userId":"DPiau3cnQ3","contestId":"NBrmAXycBH"},{"time":88.539,"username":"Artyom","userId":"ta0gMDm931","contestId":"NBrmAXycBH"},{"time":80.199,"username":"drews","userId":"BzwMxYYS3X","contestId":"NBrmAXycBH"},{"time":83.464,"username":"deel","userId":"rA15z6kfCy","contestId":"NBrmAXycBH"},{"time":90.116,"username":"Efficient","userId":"HWAtybMQXa","contestId":"NBrmAXycBH"},{"time":92.455,"username":"Yalo","userId":"hdfxdAQAs4","contestId":"NBrmAXycBH"},{"time":81.831,"username":"DimSpeed","userId":"ibqVXeSsB8","contestId":"NBrmAXycBH"},{"time":86.153,"username":"headvision","userId":"Ghwug6N5M4","contestId":"NBrmAXycBH"},{"time":82.707,"username":"Andrea","userId":"vwKVRoqmzX","contestId":"NBrmAXycBH"},{"time":81.533,"username":"Antoha","userId":"UmLPoZ7s9A","contestId":"NBrmAXycBH"},{"time":81.013,"username":"Gavryusha","userId":"IzfIutYfOb","contestId":"NBrmAXycBH"},{"time":83.0,"username":"Keine","userId":"0gspEOi6OK","contestId":"NBrmAXycBH"},{"time":91.435,"username":"marta","userId":"tO7i9RNCCw","contestId":"NBrmAXycBH"},{"time":70.891,"username":"Walrus","userId":"4tjGtcP5e0","contestId":"NBrmAXycBH"},{"time":84.14,"username":"mighty","userId":"oWyRvFZyFM","contestId":"NBrmAXycBH"}]