[{"time":84.708,"username":"Инсаф","userId":"Mg5W2rRt3g","contestId":"NQqiTjSqAm"},{"time":84.868,"username":"mighty","userId":"oWyRvFZyFM","contestId":"NQqiTjSqAm"},{"time":87.083,"username":"Kumarin","userId":"euQGYBgpDm","contestId":"NQqiTjSqAm"},{"time":87.814,"username":"dimkapimka","userId":"OscxOTzfLA","contestId":"NQqiTjSqAm"},{"time":88.436,"username":"fatok","userId":"wPJg0ahCMz","contestId":"NQqiTjSqAm"},{"time":89.145,"username":"Ixil","userId":"dCnnMPV9Eu","contestId":"NQqiTjSqAm"},{"time":90.577,"username":"aqualang","userId":"V8EQFilixt","contestId":"NQqiTjSqAm"},{"time":90.111,"username":"Solowind","userId":"Ltp2XuJpFp","contestId":"NQqiTjSqAm"},{"time":90.309,"username":"JuliaStar","userId":"fFTXkbsswP","contestId":"NQqiTjSqAm"},{"time":87.404,"username":"NoSound","userId":"OMF2I2bZbm","contestId":"NQqiTjSqAm"}]