[{"time":121.23,"username":"Aless","userId":"wSbrq0e4NY","contestId":"pvVKG9M5p7"},{"time":125.726,"username":"emerald","userId":"oKlDxpGCHc","contestId":"pvVKG9M5p7"},{"time":130.244,"username":"Andrea","userId":"vwKVRoqmzX","contestId":"pvVKG9M5p7"},{"time":127.951,"username":"Rhino","userId":"Ic0ZjHDwJy","contestId":"pvVKG9M5p7"},{"time":125.664,"username":"Chegi","userId":"T8HLBXPmVB","contestId":"pvVKG9M5p7"},{"time":128.891,"username":"Zvezdochka","userId":"JaDHISTlvW","contestId":"pvVKG9M5p7"},{"time":126.444,"username":"Kumarin","userId":"euQGYBgpDm","contestId":"pvVKG9M5p7"},{"time":128.906,"username":"drews","userId":"BzwMxYYS3X","contestId":"pvVKG9M5p7"},{"time":130.556,"username":"dimkapimka","userId":"OscxOTzfLA","contestId":"pvVKG9M5p7"}]