[{"time":84.497,"username":"chuk","userId":"KXNpCHDPFG","contestId":"QFjJnUKujU"},{"time":79.939,"username":"Managerino","userId":"qTldU0ILjC","contestId":"QFjJnUKujU"},{"time":89.324,"username":"Keine","userId":"0gspEOi6OK","contestId":"QFjJnUKujU"},{"time":80.379,"username":"Mika","userId":"8X1SzBg0JH","contestId":"QFjJnUKujU"},{"time":82.392,"username":"Droid","userId":"3vdLnr87eM","contestId":"QFjJnUKujU"},{"time":83.088,"username":"Reformer","userId":"EA2XBxV7nH","contestId":"QFjJnUKujU"},{"time":81.871,"username":"kasey","userId":"jclnmulz6T","contestId":"QFjJnUKujU"},{"time":77.745,"username":"Nikolay","userId":"XUCMOQqV2Q","contestId":"QFjJnUKujU"},{"time":82.822,"username":"sharaban","userId":"tlaCbnhUPW","contestId":"QFjJnUKujU"},{"time":86.539,"username":"ruff","userId":"v5gqt9TN4u","contestId":"QFjJnUKujU"},{"time":90.406,"username":"Coral","userId":"eS04He69a0","contestId":"QFjJnUKujU"},{"time":87.201,"username":"Rhino","userId":"Ic0ZjHDwJy","contestId":"QFjJnUKujU"},{"time":80.786,"username":"Editon","userId":"TjRmorrw4g","contestId":"QFjJnUKujU"},{"time":81.922,"username":"Ingvar","userId":"ZIAgw5cEJe","contestId":"QFjJnUKujU"},{"time":79.919,"username":"hoffman","userId":"f0hLuzIBxh","contestId":"QFjJnUKujU"},{"time":87.284,"username":"otrada","userId":"IUXKulNiDe","contestId":"QFjJnUKujU"},{"time":78.126,"username":"Gaser","userId":"G19ElWRnTA","contestId":"QFjJnUKujU"},{"time":87.961,"username":"Dilly","userId":"DPiau3cnQ3","contestId":"QFjJnUKujU"},{"time":82.513,"username":"headvision","userId":"Ghwug6N5M4","contestId":"QFjJnUKujU"},{"time":91.391,"username":"wizzle","userId":"HvY0aJUU6H","contestId":"QFjJnUKujU"},{"time":81.761,"username":"Chegi","userId":"T8HLBXPmVB","contestId":"QFjJnUKujU"},{"time":78.833,"username":"Remex","userId":"3jB2rfyCSd","contestId":"QFjJnUKujU"},{"time":81.88,"username":"Pulcer","userId":"FQLPWJDEFw","contestId":"QFjJnUKujU"},{"time":90.788,"username":"Sterl","userId":"3lh4AIdJCB","contestId":"QFjJnUKujU"},{"time":78.241,"username":"Troy","userId":"yZlVPqyl4J","contestId":"QFjJnUKujU"},{"time":83.338,"username":"mihan","userId":"oGkbP0bXcy","contestId":"QFjJnUKujU"},{"time":80.328,"username":"vasmp","userId":"w4Hn7UObSs","contestId":"QFjJnUKujU"},{"time":91.693,"username":"Garry","userId":"3rXJL0dacs","contestId":"QFjJnUKujU"},{"time":77.426,"username":"Kostik","userId":"q1Q38ckGiK","contestId":"QFjJnUKujU"},{"time":82.95,"username":"KocTuk","userId":"V2j16BXsUa","contestId":"QFjJnUKujU"},{"time":79.683,"username":"lavr","userId":"2yCcruNhxh","contestId":"QFjJnUKujU"},{"time":79.867,"username":"Gilfor","userId":"OIkFqWF7g3","contestId":"QFjJnUKujU"},{"time":84.537,"username":"Gugenot","userId":"n9AWl0ODIC","contestId":"QFjJnUKujU"},{"time":81.314,"username":"Andrea","userId":"vwKVRoqmzX","contestId":"QFjJnUKujU"},{"time":80.387,"username":"Vladislav","userId":"B5tqWjWnFA","contestId":"QFjJnUKujU"},{"time":82.355,"username":"lecter","userId":"CUGqZbAdDN","contestId":"QFjJnUKujU"}]