[{"time":89.602,"username":"Another","userId":"6nONtyMaly","contestId":"RiJIpgGR2g"},{"time":90.117,"username":"Zebra","userId":"zxy05JyuCp","contestId":"RiJIpgGR2g"},{"time":91.413,"username":"dach","userId":"eCZxH8XM0e","contestId":"RiJIpgGR2g"},{"time":95.434,"username":"Zorik","userId":"h6wgkiBBQB","contestId":"RiJIpgGR2g"},{"time":98.51,"username":"demon","userId":"HdXLaEvnq0","contestId":"RiJIpgGR2g"},{"time":90.403,"username":"Werter","userId":"bqjh0x9Lwr","contestId":"RiJIpgGR2g"},{"time":91.338,"username":"Jalex","userId":"WJJ1Sjhxre","contestId":"RiJIpgGR2g"}]