[{"time":106.729,"username":"hrizamer","userId":"ZFFubI0Vld","contestId":"RQVBpPQKvZ"},{"time":103.321,"username":"demon","userId":"HdXLaEvnq0","contestId":"RQVBpPQKvZ"},{"time":110.571,"username":"Denych","userId":"4oAHFyVqLT","contestId":"RQVBpPQKvZ"},{"time":106.39,"username":"Solowind","userId":"Ltp2XuJpFp","contestId":"RQVBpPQKvZ"},{"time":108.869,"username":"NoSound","userId":"OMF2I2bZbm","contestId":"RQVBpPQKvZ"},{"time":105.603,"username":"Might","userId":"pTvODzcpbt","contestId":"RQVBpPQKvZ"},{"time":110.617,"username":"lipton","userId":"Jba8slrEfV","contestId":"RQVBpPQKvZ"},{"time":104.786,"username":"Idall","userId":"Min24Im8Gc","contestId":"RQVBpPQKvZ"}]