[{"time":98.667999999999992,"username":"Denych","userId":"4oAHFyVqLT","contestId":"SZkXbKyGyY"},{"time":99.198000000000008,"username":"Kostik","userId":"q1Q38ckGiK","contestId":"SZkXbKyGyY"},{"time":94.476,"username":"Crazy","userId":"n1EF9yNxZ4","contestId":"SZkXbKyGyY"},{"time":91.724,"username":"truster","userId":"8bQr90wdup","contestId":"SZkXbKyGyY"},{"time":97.780999999999992,"username":"Editon","userId":"TjRmorrw4g","contestId":"SZkXbKyGyY"},{"time":101.622,"username":"dimkapimka","userId":"OscxOTzfLA","contestId":"SZkXbKyGyY"},{"time":90.544,"username":"Bokser","userId":"iFbRybereK","contestId":"SZkXbKyGyY"},{"time":91.530999999999992,"username":"adjika","userId":"QlfPptCt6n","contestId":"SZkXbKyGyY"},{"time":93.262,"username":"gazel","userId":"ZJGKTxLCSj","contestId":"SZkXbKyGyY"},{"time":99.353,"username":"svp","userId":"HHhd1jVNBP","contestId":"SZkXbKyGyY"},{"time":95.067,"username":"Tolik","userId":"xnk2S1z6Wn","contestId":"SZkXbKyGyY"},{"time":89.657999999999987,"username":"eZZg","userId":"yVcb29myV9","contestId":"SZkXbKyGyY"},{"time":96.465,"username":"Hutch","userId":"UTxdBytT5r","contestId":"SZkXbKyGyY"},{"time":96.832,"username":"yura","userId":"VTLCmSYaID","contestId":"SZkXbKyGyY"}]