[{"time":108.536,"username":"Ixil","userId":"dCnnMPV9Eu","contestId":"T05iwsWAPr"},{"time":109.318,"username":"Davidoff","userId":"jrdEiHP4UU","contestId":"T05iwsWAPr"},{"time":107.768,"username":"Stefanie","userId":"cfw9xXcIyi","contestId":"T05iwsWAPr"},{"time":107.523,"username":"hoffman","userId":"f0hLuzIBxh","contestId":"T05iwsWAPr"},{"time":105.088,"username":"chaika","userId":"ci08ZGuWC2","contestId":"T05iwsWAPr"},{"time":108.503,"username":"Sonya","userId":"E0MkSLsSdU","contestId":"T05iwsWAPr"},{"time":107.205,"username":"Gavryusha","userId":"IzfIutYfOb","contestId":"T05iwsWAPr"},{"time":109.948,"username":"Gaser","userId":"G19ElWRnTA","contestId":"T05iwsWAPr"}]