[{"time":183.345,"username":"yura","userId":"VTLCmSYaID","contestId":"uSnzt3ckUq"},{"time":185.792,"username":"Gugenot","userId":"n9AWl0ODIC","contestId":"uSnzt3ckUq"},{"time":199.302,"username":"eZZg","userId":"yVcb29myV9","contestId":"uSnzt3ckUq"},{"time":199.237,"username":"Energizer","userId":"r6y3GpAYZd","contestId":"uSnzt3ckUq"},{"time":199.196,"username":"Scorpion","userId":"Fv5hg1ehgW","contestId":"uSnzt3ckUq"},{"time":188.949,"username":"krasom","userId":"8T06DI3NK5","contestId":"uSnzt3ckUq"},{"time":187.185,"username":"Idall","userId":"Min24Im8Gc","contestId":"uSnzt3ckUq"},{"time":188.763,"username":"Antoha","userId":"UmLPoZ7s9A","contestId":"uSnzt3ckUq"},{"time":191.145,"username":"Efficient","userId":"HWAtybMQXa","contestId":"uSnzt3ckUq"},{"time":192.998,"username":"Might","userId":"pTvODzcpbt","contestId":"uSnzt3ckUq"},{"time":202.855,"username":"s4n9","userId":"ai5Juu7L58","contestId":"uSnzt3ckUq"}]