[{"time":74.764,"username":"Margo","userId":"2ClZvL60Ff","contestId":"uUg2GmKOyT"},{"time":68.421,"username":"Ixil","userId":"dCnnMPV9Eu","contestId":"uUg2GmKOyT"},{"time":61.893,"username":"Evgeny","userId":"fwKazCpkqh","contestId":"uUg2GmKOyT"},{"time":81.136,"username":"sharaban","userId":"tlaCbnhUPW","contestId":"uUg2GmKOyT"},{"time":75.102,"username":"theone","userId":"zhi8GC7Y2n","contestId":"uUg2GmKOyT"},{"time":82.04,"username":"mrqrush","userId":"le9hmvK2YC","contestId":"uUg2GmKOyT"},{"time":68.074,"username":"Bravenheart","userId":"gQN94BczW1","contestId":"uUg2GmKOyT"},{"time":68.068,"username":"bodiroga","userId":"TFcY4B2JsF","contestId":"uUg2GmKOyT"},{"time":69.10799999999999,"username":"aqualang","userId":"V8EQFilixt","contestId":"uUg2GmKOyT"},{"time":61.655,"username":"mighty","userId":"oWyRvFZyFM","contestId":"uUg2GmKOyT"},{"time":75.789,"username":"turonix","userId":"x9vZrPl0e6","contestId":"uUg2GmKOyT"},{"time":71.13000000000001,"username":"thunderstorm","userId":"ss2WVEVHi3","contestId":"uUg2GmKOyT"},{"time":64.497,"username":"Spark","userId":"m6551zkLFi","contestId":"uUg2GmKOyT"},{"time":68.682,"username":"eZZg","userId":"yVcb29myV9","contestId":"uUg2GmKOyT"},{"time":65.245,"username":"Alexander","userId":"FtPNo0wmUz","contestId":"uUg2GmKOyT"},{"time":55.687,"username":"Sterl","userId":"3lh4AIdJCB","contestId":"uUg2GmKOyT"},{"time":67.365,"username":"Gavryusha","userId":"IzfIutYfOb","contestId":"uUg2GmKOyT"},{"time":58.975,"username":"wizzle","userId":"HvY0aJUU6H","contestId":"uUg2GmKOyT"},{"time":69.819,"username":"Stenli","userId":"PPpEK97LbY","contestId":"uUg2GmKOyT"},{"time":78.955,"username":"Thunderbird","userId":"l2AZobIsml","contestId":"uUg2GmKOyT"},{"time":69.04,"username":"Yaroslav","userId":"pKKThXr0og","contestId":"uUg2GmKOyT"},{"time":66.466,"username":"Zorik","userId":"h6wgkiBBQB","contestId":"uUg2GmKOyT"},{"time":81.292,"username":"Werter","userId":"bqjh0x9Lwr","contestId":"uUg2GmKOyT"},{"time":83.642,"username":"Jobru","userId":"QyLF17xoue","contestId":"uUg2GmKOyT"},{"time":75.041,"username":"chaika","userId":"ci08ZGuWC2","contestId":"uUg2GmKOyT"}]