[{"time":74.1,"username":"proando","userId":"65IZ97rieY","contestId":"wOpeowwbfw"},{"time":86.887999999999991,"username":"defender","userId":"fafCy9FcG5","contestId":"wOpeowwbfw"},{"time":77.178999999999988,"username":"Stenli","userId":"PPpEK97LbY","contestId":"wOpeowwbfw"},{"time":78.097000000000008,"username":"realtor","userId":"xughIg536p","contestId":"wOpeowwbfw"},{"time":85.378,"username":"Artem","userId":"EWRf6hAaNP","contestId":"wOpeowwbfw"},{"time":76.457,"username":"Nikolay","userId":"XUCMOQqV2Q","contestId":"wOpeowwbfw"},{"time":76.215,"username":"Noir","userId":"48MwdVABxn","contestId":"wOpeowwbfw"},{"time":81.662,"username":"krasom","userId":"8T06DI3NK5","contestId":"wOpeowwbfw"},{"time":81.25800000000001,"username":"Zorik","userId":"h6wgkiBBQB","contestId":"wOpeowwbfw"},{"time":72.079000000000008,"username":"Ingvar","userId":"ZIAgw5cEJe","contestId":"wOpeowwbfw"},{"time":81.393,"username":"Ofigist","userId":"Xc0W00RPcD","contestId":"wOpeowwbfw"},{"time":76.39,"username":"Roman","userId":"IQnLwda1cb","contestId":"wOpeowwbfw"},{"time":82.454,"username":"Artemchik","userId":"ElLFHDPZOE","contestId":"wOpeowwbfw"},{"time":74.452999999999989,"username":"demon","userId":"HdXLaEvnq0","contestId":"wOpeowwbfw"},{"time":85.73,"username":"sunset","userId":"PKmLfKc1JZ","contestId":"wOpeowwbfw"},{"time":84.755,"username":"diezel","userId":"Qu9nKCtD1O","contestId":"wOpeowwbfw"},{"time":83.516,"username":"Terra","userId":"pIy71rR1ZN","contestId":"wOpeowwbfw"},{"time":79.396,"username":"kosmarium","userId":"t3uLSkjM2J","contestId":"wOpeowwbfw"},{"time":75.688,"username":"Coral","userId":"eS04He69a0","contestId":"wOpeowwbfw"}]