[{"time":44.244,"username":"AZis","userId":"r4kvdWPlLA","contestId":"X6IDo5jVKR"},{"time":44.278,"username":"takumi","userId":"FYxjOFE7BV","contestId":"X6IDo5jVKR"},{"time":44.049,"username":"alchemist","userId":"pNih4vtYln","contestId":"X6IDo5jVKR"},{"time":41.414,"username":"noBody","userId":"xWZwOiUgsG","contestId":"X6IDo5jVKR"},{"time":39.63,"username":"kasey","userId":"jclnmulz6T","contestId":"X6IDo5jVKR"},{"time":40.976,"username":"Jalex","userId":"WJJ1Sjhxre","contestId":"X6IDo5jVKR"},{"time":42.336,"username":"Zvezdochka","userId":"JaDHISTlvW","contestId":"X6IDo5jVKR"},{"time":43.171,"username":"Editon","userId":"TjRmorrw4g","contestId":"X6IDo5jVKR"},{"time":40.071,"username":"emerald","userId":"oKlDxpGCHc","contestId":"X6IDo5jVKR"},{"time":40.311,"username":"Teufel","userId":"2d8J4OGIuM","contestId":"X6IDo5jVKR"},{"time":44.18,"username":"Ixil","userId":"dCnnMPV9Eu","contestId":"X6IDo5jVKR"},{"time":46.898,"username":"Xlat","userId":"WtV2U0BpZZ","contestId":"X6IDo5jVKR"},{"time":41.599,"username":"Fiolent","userId":"Hv2K0RxqA1","contestId":"X6IDo5jVKR"},{"time":40.663,"username":"Crazy","userId":"n1EF9yNxZ4","contestId":"X6IDo5jVKR"},{"time":50.49,"username":"Yaroslav","userId":"pKKThXr0og","contestId":"X6IDo5jVKR"},{"time":45.876,"username":"Garry","userId":"3rXJL0dacs","contestId":"X6IDo5jVKR"},{"time":48.217,"username":"Rhino","userId":"Ic0ZjHDwJy","contestId":"X6IDo5jVKR"},{"time":42.251,"username":"shurisk","userId":"1V6lDDKVey","contestId":"X6IDo5jVKR"},{"time":43.774,"username":"Davidoff","userId":"jrdEiHP4UU","contestId":"X6IDo5jVKR"},{"time":42.813,"username":"KocTuk","userId":"V2j16BXsUa","contestId":"X6IDo5jVKR"},{"time":40.718,"username":"Gugenot","userId":"n9AWl0ODIC","contestId":"X6IDo5jVKR"},{"time":42.601,"username":"terminator","userId":"mvZuv4N7TI","contestId":"X6IDo5jVKR"},{"time":39.197,"username":"Vladislav","userId":"B5tqWjWnFA","contestId":"X6IDo5jVKR"},{"time":40.172,"username":"turonix","userId":"x9vZrPl0e6","contestId":"X6IDo5jVKR"},{"time":41.811,"username":"snaips","userId":"iajU4vqzRc","contestId":"X6IDo5jVKR"},{"time":41.643,"username":"Antoha","userId":"UmLPoZ7s9A","contestId":"X6IDo5jVKR"},{"time":51.689,"username":"Gavryusha","userId":"IzfIutYfOb","contestId":"X6IDo5jVKR"},{"time":50.672,"username":"Efficient","userId":"HWAtybMQXa","contestId":"X6IDo5jVKR"},{"time":44.37,"username":"Cherepov","userId":"oq0k6irY13","contestId":"X6IDo5jVKR"},{"time":41.385,"username":"gazel","userId":"ZJGKTxLCSj","contestId":"X6IDo5jVKR"},{"time":44.181,"username":"Andrea","userId":"vwKVRoqmzX","contestId":"X6IDo5jVKR"},{"time":46.866,"username":"twist","userId":"AcLDEezjQ4","contestId":"X6IDo5jVKR"},{"time":42.004,"username":"diezel","userId":"Qu9nKCtD1O","contestId":"X6IDo5jVKR"},{"time":53.612,"username":"maxat","userId":"Xr41F2cAdl","contestId":"X6IDo5jVKR"},{"time":51.272,"username":"Coral","userId":"eS04He69a0","contestId":"X6IDo5jVKR"},{"time":48.895,"username":"extonec","userId":"ygSBoV8tCx","contestId":"X6IDo5jVKR"}]