[{"time":44.013999999999996,"username":"Sensi","userId":"jRy3fU7oKL","contestId":"xlAiB0D2kR"},{"time":42.035,"username":"Stitch","userId":"Za1HN3dNKl","contestId":"xlAiB0D2kR"},{"time":49.942,"username":"Zorik","userId":"h6wgkiBBQB","contestId":"xlAiB0D2kR"},{"time":49.052,"username":"dach","userId":"eCZxH8XM0e","contestId":"xlAiB0D2kR"},{"time":43.41,"username":"lavr","userId":"2yCcruNhxh","contestId":"xlAiB0D2kR"},{"time":44.377,"username":"bodiroga","userId":"TFcY4B2JsF","contestId":"xlAiB0D2kR"},{"time":42.922,"username":"Droid","userId":"3vdLnr87eM","contestId":"xlAiB0D2kR"},{"time":44.444,"username":"uckpa","userId":"Y1UmUYmyL3","contestId":"xlAiB0D2kR"},{"time":47.101,"username":"Artem","userId":"EWRf6hAaNP","contestId":"xlAiB0D2kR"},{"time":47.471999999999994,"username":"yura","userId":"VTLCmSYaID","contestId":"xlAiB0D2kR"},{"time":47.196000000000005,"username":"Moster","userId":"M8PQoBaihj","contestId":"xlAiB0D2kR"},{"time":46.997,"username":"Korobochka","userId":"tEjWG0LH5b","contestId":"xlAiB0D2kR"},{"time":49.572,"username":"Telecom","userId":"xa5SQIppDN","contestId":"xlAiB0D2kR"},{"time":47.766999999999996,"username":"terminator","userId":"mvZuv4N7TI","contestId":"xlAiB0D2kR"},{"time":43.111,"username":"Troy","userId":"yZlVPqyl4J","contestId":"xlAiB0D2kR"},{"time":42.512,"username":"dereviashkina","userId":"8lIWVSzXwI","contestId":"xlAiB0D2kR"},{"time":48.707,"username":"Margo","userId":"2ClZvL60Ff","contestId":"xlAiB0D2kR"},{"time":43.37,"username":"Gore","userId":"p0wy1dsDD2","contestId":"xlAiB0D2kR"},{"time":42.572,"username":"Roman","userId":"IQnLwda1cb","contestId":"xlAiB0D2kR"}]