[{"time":26.763,"username":"Duid","userId":"0E3AWyhUKX","contestId":"YPHAQFmmY9"},{"time":38.884,"username":"Artemchik","userId":"ElLFHDPZOE","contestId":"YPHAQFmmY9"},{"time":40.772,"username":"Fess","userId":"vuTXE5XseP","contestId":"YPHAQFmmY9"},{"time":36.377,"username":"radda","userId":"MwkCKKWbak","contestId":"YPHAQFmmY9"},{"time":36.406,"username":"emerald","userId":"oKlDxpGCHc","contestId":"YPHAQFmmY9"},{"time":28.909,"username":"Mikaber","userId":"MRzKYSGZNH","contestId":"YPHAQFmmY9"},{"time":41.05,"username":"Nikolay","userId":"XUCMOQqV2Q","contestId":"YPHAQFmmY9"},{"time":30.902,"username":"maxat","userId":"Xr41F2cAdl","contestId":"YPHAQFmmY9"},{"time":40.857,"username":"satair","userId":"glMXrooxoW","contestId":"YPHAQFmmY9"},{"time":27.363,"username":"Artyom","userId":"ta0gMDm931","contestId":"YPHAQFmmY9"},{"time":43.65,"username":"Infa","userId":"E6SXFmqkmd","contestId":"YPHAQFmmY9"},{"time":39.42,"username":"Koenigsberg","userId":"O8X8cUgw5R","contestId":"YPHAQFmmY9"},{"time":27.318,"username":"greenstar","userId":"2ETM6KN9sT","contestId":"YPHAQFmmY9"},{"time":36.627,"username":"nagel","userId":"dVkcFX0cE1","contestId":"YPHAQFmmY9"},{"time":32.78,"username":"arverson","userId":"w0JFdFKANi","contestId":"YPHAQFmmY9"},{"time":36.473,"username":"murr","userId":"wTrwQLDgos","contestId":"YPHAQFmmY9"},{"time":40.576,"username":"playa","userId":"6hceWKjc9h","contestId":"YPHAQFmmY9"},{"time":32.204,"username":"Sonya","userId":"E0MkSLsSdU","contestId":"YPHAQFmmY9"},{"time":29.052,"username":"AZis","userId":"r4kvdWPlLA","contestId":"YPHAQFmmY9"},{"time":31.314,"username":"turonix","userId":"x9vZrPl0e6","contestId":"YPHAQFmmY9"},{"time":39.227,"username":"Stenli","userId":"PPpEK97LbY","contestId":"YPHAQFmmY9"},{"time":35.421,"username":"German","userId":"lT33kiOL4T","contestId":"YPHAQFmmY9"},{"time":40.191,"username":"Riba","userId":"KE3b7mCwto","contestId":"YPHAQFmmY9"},{"time":38.919,"username":"Kumarin","userId":"euQGYBgpDm","contestId":"YPHAQFmmY9"},{"time":38.446,"username":"shoma","userId":"MUeDjXVL0E","contestId":"YPHAQFmmY9"},{"time":27.577,"username":"KocTuk","userId":"V2j16BXsUa","contestId":"YPHAQFmmY9"},{"time":31.945,"username":"dimas","userId":"N3KstJQA9W","contestId":"YPHAQFmmY9"},{"time":41.22,"username":"Gugenot","userId":"n9AWl0ODIC","contestId":"YPHAQFmmY9"},{"time":37.111,"username":"Jalex","userId":"WJJ1Sjhxre","contestId":"YPHAQFmmY9"},{"time":35.923,"username":"andalus","userId":"uNj4gR9I2j","contestId":"YPHAQFmmY9"},{"time":43.408,"username":"Achilles","userId":"o0weiufq4s","contestId":"YPHAQFmmY9"},{"time":26.807,"username":"Zebra","userId":"zxy05JyuCp","contestId":"YPHAQFmmY9"},{"time":27.46,"username":"bodiroga","userId":"TFcY4B2JsF","contestId":"YPHAQFmmY9"},{"time":38.949,"username":"Oxbla","userId":"XlYsTfOQ7t","contestId":"YPHAQFmmY9"},{"time":33.175,"username":"drews","userId":"BzwMxYYS3X","contestId":"YPHAQFmmY9"},{"time":41.046,"username":"mighty","userId":"oWyRvFZyFM","contestId":"YPHAQFmmY9"},{"time":34.633,"username":"Spark","userId":"m6551zkLFi","contestId":"YPHAQFmmY9"},{"time":40.236,"username":"JuliaStar","userId":"fFTXkbsswP","contestId":"YPHAQFmmY9"},{"time":39.635,"username":"Walrus","userId":"4tjGtcP5e0","contestId":"YPHAQFmmY9"},{"time":36.021,"username":"mihan","userId":"oGkbP0bXcy","contestId":"YPHAQFmmY9"},{"time":36.273,"username":"tiger","userId":"E13LiAUW4M","contestId":"YPHAQFmmY9"},{"time":30.458,"username":"Werter","userId":"bqjh0x9Lwr","contestId":"YPHAQFmmY9"}]