[{"time":74.761,"username":"Droid","userId":"3vdLnr87eM","contestId":"zxtTY1X6zx"},{"time":66.9,"username":"funesto","userId":"u069ZGm6EU","contestId":"zxtTY1X6zx"},{"time":68.969,"username":"Artyom","userId":"ta0gMDm931","contestId":"zxtTY1X6zx"},{"time":73.293,"username":"Artem","userId":"EWRf6hAaNP","contestId":"zxtTY1X6zx"},{"time":74.218,"username":"mori","userId":"YSiAgFzgRt","contestId":"zxtTY1X6zx"},{"time":66.307,"username":"dach","userId":"eCZxH8XM0e","contestId":"zxtTY1X6zx"},{"time":67.691,"username":"Wrecker","userId":"wgU9D2McZ9","contestId":"zxtTY1X6zx"},{"time":68.367,"username":"kryab","userId":"MxZLOYn3Xe","contestId":"zxtTY1X6zx"},{"time":74.152,"username":"defender","userId":"fafCy9FcG5","contestId":"zxtTY1X6zx"}]